Workbook

Sheet Read Me
A1: Centience partner referral contacts
A2: Source: Apollo.io people search + bulk enrichment, August 2026. 183 credits. Zero missing records across four waves.
A3: Built from partner-referral-contacts-ALL.csv in docs/marketing/. Strategy, commission tiers and legal guardrails live in partner-referral-program.md.
A5: Sheets
A6: Summary — counts by tier and email status. All formulas over All Contacts.
A7: All Contacts — every one of the 170 rows. Filter/sort freely; the Summary follows.
A8: Send List — one contact per firm (93 rows). This is the real campaign size, not 170.
A10: Fill these in (yellow cells on Send List)
A11: Owner · Status · Date contacted · Notes are blank for you. Nothing else needs editing.
A12: Example row: Owner "Orville" · Status "Replied — call booked" · Date contacted 2026-08-11 · Notes "Wants co-branded Score for 2 clients"
A14: Before you send
A15: ONE FIRM IS ONE RELATIONSHIP. "Contacts at firm" > 1 means alternates exist; they are fallbacks, not extra targets. Emailing three founding principals at one firm in a week reads as a scrape.
... A29: The Summary tab is formula-driven. This file was written by a script, so formula cells hold no cached value until Excel opens and calculates them — that happens automatically on open, and every function used (COUNTA, COUNTIF, SUMPRODUCT, SUM) is standard. Expected results are printed beside each figure on Summary so a wrong number is obvious.

Sheet Summary
A1: Centience partner referral list — summary
A2: All figures are formulas over the All Contacts sheet; they update if you edit or filter that data.
A4: Metric | B4: Count
A5: Contacts | B5: =COUNTA('All Contacts'!B2:B171) | D5: Expected: 170
A6: Distinct firms | B6: =SUMPRODUCT((('All Contacts'!D2:D171<>"")/COUNTIF('All Contacts'!D2:D171,'All Contacts'!D2:D171&""))) | D6: Expected: 93
A7: LinkedIn profiles | B7: =COUNTA('All Contacts'!I2:I171) | D7: Expected: 170
A8: Verified email | B8: =COUNTIF('All Contacts'!H2:H171,"verified") | D8: Expected: 152
A9: Guessed email (extrapolated) | B9: =COUNTIF('All Contacts'!H2:H171,"extrapolated") | D9: Expected: 2
A10: No email — LinkedIn only | B10: =COUNTIF('All Contacts'!H2:H171,"unavailable") | D10: Expected: 16
A11: Send List rows (1 per firm) | B11: =COUNTA('Send List'!B2:B94) | D11: Expected: 93
A13: Tier | B13: Contacts | C13: Firms
A14: Boutique compliance | B14: =COUNTIF('All Contacts'!A2:A171,A14) | C14: =COUNTIF('Send List'!A2:A94,A14)
A15: Compliance (national) | B15: =COUNTIF('All Contacts'!A2:A171,A15) | C15: =COUNTIF('Send List'!A2:A94,A15)
A16: Enterprise compliance | B16: =COUNTIF('All Contacts'!A2:A171,A16) | C16: =COUNTIF('Send List'!A2:A94,A16)
A17: Compliance + legal | B17: =COUNTIF('All Contacts'!A2:A171,A17) | C17: =COUNTIF('Send List'!A2:A94,A17)
A18: Cyber / E&O broker | B18: =COUNTIF('All Contacts'!A2:A171,A18) | C18: =COUNTIF('Send List'!A2:A94,A18)
A19: RIA platform | B19: =COUNTIF('All Contacts'!A2:A171,A19) | C19: =COUNTIF('Send List'!A2:A94,A19)
A20: Fund administrator | B20: =COUNTIF('All Contacts'!A2:A171,A20) | C20: =COUNTIF('Send List'!A2:A94,A20)
A21: RIA M&A advisor | B21: =COUNTIF('All Contacts'!A2:A171,A21) | C21: =COUNTIF('Send List'!A2:A94,A21)
A22: Securities counsel | B22: =COUNTIF('All Contacts'!A2:A171,A22) | C22: =COUNTIF('Send List'!A2:A94,A22)
A23: Adjacent / weaker fit | B23: =COUNTIF('All Contacts'!A2:A171,A23) | C23: =COUNTIF('Send List'!A2:A94,A23)
A24: Total | B24: =SUM(B14:B23) | C24: =SUM(C14:C23)
A26: Cells B5:C24 are formulas. Excel computes them the moment you open this file. If any figure differs from the "Expected" note beside it, the sheet was filtered or edited — recheck before relying on it.

Sheet All Contacts
A1: Tier | B1: Name | C1: Title | D1: Firm | E1: Contacts at firm | F1: Firm domain | G1: Work email | H1: Email status | I1: LinkedIn profile | J1: Location | K1: Firm phone | L1: Wave | M1: Apollo person ID
A2: Boutique compliance | B2: Vick Ekizian | C2: Founder and CEO | D2: 5 Pillars Compliance Consulting, LLC | E2: 1 | F2: 5pillarscompliance.com | G2: vick@5pillarscompliance.com | H2: verified | I2: /in/vickekizian | J2: Los Angeles California | K2: +1 818-523-9762 | L2: 1 | M2: 55706c157369646bf4db1500
A3: Boutique compliance | B3: Lisa Roitman | C3: Managing Partner | D3: Abide Consulting Group | E3: 3 | F3: abidegrp.com | G3: lisa@abidegrp.com | H3: verified | I3: /in/lisaroitman | J3: New York New York | K3: +1 212-362-4598 | L3: 1 | M3: 600f16e2bc34ca00016944cf
A4: Boutique compliance | B4: Patrick Harris | C4: Managing Director | D4: Abide Consulting Group | E4: 3 | F4: abidegrp.com | H4: unavailable | I4: /in/patrickeharris | J4: New York New York | K4: +1 212-362-4598 | L4: 2 | M4: 57dbbfc8a6da9868dafa2010
A5: Boutique compliance | B5: Pete Galloway | C5: Managing Partner | D5: Abide Consulting Group | E5: 3 | F5: abidegrp.com | G5: pete@abidegrp.com | H5: verified | I5: /in/petegalloway | J5: Denver Colorado | K5: +1 212-362-4598 | L5: 1 | M5: 54a48b1c7468692abf729a4f
A6: Boutique compliance | B6: Robert Masi | C6: Managing Partner | D6: Accordo | E6: 1 | F6: accordo.solutions | G6: robert.masi@accordo.solutions | H6: verified | I6: /in/robert-masi-1a123b8 | J6: New York New York | K6: +1 646-868-8150 | L6: 2 | M6: 66ed6833f501800001ee423f
A7: Boutique compliance | B7: Giselle Casella | C7: Vice President and Partner | D7: Adviser Compliance Consulting | E7: 2 | F7: outsourcecco.com | G7: gcasella@outsourcecco.com | H7: verified | I7: /in/giselle-casella-62090310 | J7: Naples Florida | K7: +1 650-703-2159 | L7: 1 | M7: 67000b23fd887b0001345983
A8: Boutique compliance | B8: Stephen Lurie | C8: Principal Owner | D8: Adviser Compliance Consulting | E8: 2 | F8: outsourcecco.com | H8: unavailable | I8: /in/stephen-lurie-8b0b371 | J8: New York New York | K8: +1 650-703-2159 | L8: 1 | M8: 610a381ea614ea00018458e2
A9: Boutique compliance | B9: Joseph Stowell | C9: Managing Partner, President | D9: Ally Compliance Partners LLC | E9: 1 | F9: allycompliancepartners.com | G9: joe@allycompliancepartners.com | H9: verified | I9: /in/josephstowell | J9: Londonderry New Hampshire | K9: +1 617-304-0117 | L9: 1 | M9: 5b89436c324d443417b428b7
A10: Boutique compliance | B10: Chris Hardy | C10: Co-Founder | D10: altPILOT Group | E10: 2 | F10: altpilotgroup.com | G10: chris@altpilotgroup.com | H10: verified | I10: /in/chrishardy2 | J10: New York New York | K10: +1 786-473-8090 | L10: 2 | M10: 59399c00a6da9817851bc60b
A11: Boutique compliance | B11: Korrine Kohm | C11: Managing Director | D11: altPILOT Group | E11: 2 | F11: altpilotgroup.com | G11: korrine@altpilotgroup.com | H11: verified | I11: /in/korrine-kohm-816417a | J11: New York New York | K11: +1 786-473-8090 | L11: 2 | M11: 60388f2cec817900010fb78d
A12: Boutique compliance | B12: Eden Turner | C12: Managing Director, Compliance and Risk Management | D12: Asgard Regulatory Group, LLC | E12: 3 | F12: asgardcompliance.com | G12: eturner@asgardcompliance.com | H12: verified | I12: /in/eden-turner-9b08a487 | J12: Oakdale New York | K12: +1 631-801-2900 | L12: 2 | M12: 54a206837468693cdd834906
A13: Boutique compliance | B13: Jon Hurd | C13: Founder, Chief Executive Officer and Certified Anti-Money Laundering Specialist | D13: Asgard Regulatory Group, LLC | E13: 3 | F13: asgardcompliance.com | G13: jhurd@asgardcompliance.com | H13: verified | I13: /in/jonhurdarg | J13: Holbrook New York | K13: +1 631-801-2900 | L13: 2 | M13: 66fe0e657932dd0001e89c77
A14: Boutique compliance | B14: Patrick Kane | C14: Managing Director | D14: Asgard Regulatory Group, LLC | E14: 3 | F14: asgardcompliance.com | G14: pkane@asgardcompliance.com | H14: verified | I14: /in/patrick-kane-7010855 | J14: New York New York | K14: +1 631-801-2900 | L14: 2 | M14: 5acf19dfa6da98d0d0b444d4
A15: Boutique compliance | B15: Jordan Jasser | C15: Partner, President | D15: Aspect Advisors | E15: 6 | F15: aspectadv.com | G15: jordan@aspectadv.com | H15: verified | I15: /in/jordan-jasser-0346b070 | J15: New York New York | K15: +1 415-423-3445 | L15: 2 | M15: 66f6f0e857022d000128cff6
A16: Boutique compliance | B16: Justin Schleifer | C16: President, Co-Founder | D16: Aspect Advisors | E16: 6 | F16: aspectadv.com | G16: justin@aspectadv.com | H16: verified | I16: /in/justin-schleifer-28852036 | J16: New York New York | K16: +1 415-423-3445 | L16: 2 | M16: 66fb2df8518a660001e69ef0
A17: Boutique compliance | B17: Chris Nowak | C17: Founder & CEO | D17: Augmenta Prime | E17: 1 | F17: augmentaprimegroup.com | G17: chris.nowak@augmentaprimegroup.com | H17: verified | I17: /in/chris-nowak-cams-cafp-cbp | J17: New York | L17: 2 | M17: 67183a61bd462b0001c870b7
A18: Boutique compliance | B18: Colleen Kelly | C18: Managing Director | D18: Chenery Compliance Group | E18: 4 | F18: chenerycompliance.com | G18: ckelly@chenerycompliance.com | H18: verified | I18: /in/colleen-kelly-aif%c2%ae-b2088523 | J18: Ashburn Virginia | K18: +1 484-464-0300 | L18: 1 | M18: 60afd5041203cc00014edd51
A19: Boutique compliance | B19: Craig Moreshead | C19: Managing Director | D19: Chenery Compliance Group | E19: 4 | F19: chenerycompliance.com | G19: cmoreshead@chenerycompliance.com | H19: verified | I19: /in/craigmoreshead | J19: West Palm Beach Florida | K19: +1 484-464-0300 | L19: 1 | M19: 54aab3aa7468690630efff13
A20: Boutique compliance | B20: Stefanie Little | C20: Founder & Managing Partner | D20: Chenery Compliance Group | E20: 4 | F20: chenerycompliance.com | G20: slittle@chenerycompliance.com | H20: verified | I20: /in/stefanie-j-little-b155075 | J20: Elkton Maryland | K20: +1 484-464-0300 | L20: 1 | M20: 66fc1f0a3b5eed0001a5e371
A21: Boutique compliance | B21: Thomas Cain | C21: Founder & Managing Partner | D21: Chenery Compliance Group | E21: 4 | F21: chenerycompliance.com | G21: tdecain@chenerygroup.com | H21: verified | I21: /in/tdecain | J21: New York New York | K21: +1 484-464-0300 | L21: 2 | M21: 66f68f29e2b6530001c3b866
A22: Boutique compliance | B22: Claire McCleskey | C22: Co-Founder | D22: Clarity Compliance Consulting | E22: 1 | F22: clarity-consultancy.com | G22: com@clarity-consultancy.com | H22: verified | I22: /in/claire-o-neill-mccleskey | J22: New York New York | L22: 2 | M22: 611a8d85b40c3e0001a54a09
A23: Boutique compliance | B23: David Martin | C23: Founder/CEO | D23: Compliers Consulting Services, LLC | E23: 2 | F23: compliers.com | G23: david@compliers.com | H23: verified | I23: /in/davidjaindlmartin | J23: New York New York | K23: +1 917-345-2461 | L23: 2 | M23: 60cf4bb6becbc70001bd6490
A24: Boutique compliance | B24: Michelle Jacko | C24: CEO | D24: Core Compliance & Legal Services, Inc. | E24: 1 | F24: corecls.com | G24: michelle.jacko@corecls.com | H24: verified | I24: /in/michellejacko | J24: San Diego California | K24: +1 619-278-0020 | L24: 1 | M24: 68cf57da40b35e00013a604e
A25: Boutique compliance | B25: Gary Fox | C25: Managing Director and Partner | D25: DFP Partners | E25: 2 | F25: dfppartners.com | G25: gfox@dfppartners.com | H25: verified | I25: /in/garyfox8 | J25: New York New York | K25: +1 212-751-4422 | L25: 2 | M25: 5fa2428f3770bf0001a19d82
A26: Boutique compliance | B26: Michael Glynn | C26: Principal | D26: DFP Partners | E26: 2 | F26: dfppartners.com | G26: mglynn@sddco.com | H26: verified | I26: /in/michael-glynn-6453575 | J26: New York New York | K26: +1 212-751-4422 | L26: 2 | M26: 5ac982f7a6da9840f6312264
A27: Boutique compliance | B27: Daniel Garcia | C27: Principal Compliance Officer at InnReg | D27: InnReg | E27: 2 | F27: innreg.com | G27: daniel@innreg.com | H27: verified | I27: /in/daniel-garcia-b67a1723 | J27: Fort Lauderdale Florida | K27: +1 305-908-1160 | L27: 2 | M27: 5e7c809a64ba4100017cdb37
A28: Boutique compliance | B28: Francesco Matteini | C28: CEO and Founder | D28: InnReg | E28: 2 | F28: innreg.com | G28: francesco@innreg.com | H28: verified | I28: /in/fmatteini | J28: Miami Florida | K28: +1 305-908-1160 | L28: 2 | M28: 66f438a547af530001b9576b
A29: Boutique compliance | B29: Stephen Murphy | C29: Managing Director | D29: Integrated Compliance Consulting | E29: 2 | F29: integratedcomplianceconsulting.com | G29: smurphy@icc-comply.com | H29: verified | I29: /in/stephen-murphy-cfa-9903874 | L29: 1 | M29: 5fd08a11d173d6000193434a
A30: Boutique compliance | B30: Trish Davis | C30: Managing Director | D30: Integrated Compliance Consulting | E30: 2 | F30: integratedcomplianceconsulting.com | G30: tdavis@integratedcomplianceconsulting.com | H30: verified | I30: /in/trish-davis-4a1668298 | J30: Maize Kansas | L30: 1 | M30: 668cea1a7921f3000181c0e6
A31: Boutique compliance | B31: Jennifer Mascioli-Tudor | C31: Founder and Principal Consultant | D31: JMT Compliance Consulting | E31: 1 | F31: jmtcompliance.com | G31: jennifer@jmtcompliance.com | H31: verified | I31: /in/jennifermascioli | J31: San Francisco California | L31: 1 | M31: 66f11ab66453d300019f27a1
A32: Boutique compliance | B32: Matthew Swendiman | C32: President and Chief Executive Officer | D32: Key Bridge Compliance | E32: 1 | F32: keybridgecompliance.com | G32: mswendiman@keybridgecompliance.com | H32: verified | I32: /in/matthewswendiman | J32: Cincinnati Ohio | K32: +1 859-308-3246 | L32: 1 | M32: 66fd80a967622700018dd038
A33: Boutique compliance | B33: Luisa Franco | C33: CEO & Founder | D33: LFP Risk Solutions | E33: 1 | F33: lfprisksolutions.com | G33: luisa@lfprisksolutions.com | H33: verified | I33: /in/luisafranco1 | J33: New York New York | K33: +1 908-956-3755 | L33: 2 | M33: 66ff99f7ad0d090001ba4d4f
A34: Boutique compliance | B34: Ken Norensberg | C34: Chief Executive Officer | D34: Luxor Financial Group/Broker Dealer/Registered Investment Adviser Experts | E34: 1 | F34: luxorbd.com | G34: ken@luxorbd.com | H34: verified | I34: /in/kennorensberg | J34: New York New York | K34: +1 888-521-8858 | L34: 2 | M34: 55706d89736964704f7d2100
A35: Boutique compliance | B35: Giovanni Corrado | C35: CEO | D35: NextReg | E35: 1 | F35: thenextreg.com | G35: gio@thenextreg.com | H35: verified | I35: /in/giovannicorrado1 | J35: Miami Florida | L35: 2 | M35: 5cf82b27f6512513c23e9949
A36: Boutique compliance | B36: Victoria Hogan | C36: President | D36: NorthPoint Compliance LLC | E36: 1 | F36: npcomply.com | G36: vhogan@npcomply.com | H36: verified | I36: /in/victoria-g-hogan-cfa-331217a | J36: New York New York | K36: +1 732-778-5488 | L36: 2 | M36: 66ec3cbbc381350001a2ac5a
A37: Boutique compliance | B37: Jonathan Saxton | C37: CEO/Founder | D37: Optima Partners | E37: 5 | F37: optima-partners.com | G37: jonathan.saxton@optima-partners.com | H37: verified | I37: /in/jonathan-saxton-12588013 | J37: New York New York | K37: +1 646-205-6380 | L37: 2 | M37: 611c2c1c0a01cc0001072ca7
A38: Boutique compliance | B38: Steve Boyd | C38: Principal | D38: Optima Partners | E38: 5 | F38: optima-partners.com | G38: stephen.boyd@optima-partners.com | H38: verified | I38: /in/steve-b-249a2564 | J38: Miami Florida | K38: +1 646-205-6380 | L38: 2 | M38: 672cdb7d47f6880001bfe6c7
A39: Boutique compliance | B39: Pawneet Abramowski | C39: CEO & Founder | D39: PARC Solutions | E39: 1 | F39: parcsolutionsllc.com | G39: pawneet@parcsolutionsllc.com | H39: verified | I39: /in/pawneet | J39: New York New York | L39: 2 | M39: 67004878fb7271000159de31
A40: Boutique compliance | B40: David Lombardy | C40: Founder and Principal | D40: Pillar Compliance Group | E40: 1 | F40: pillarcompliance.com | G40: dlombardy@pillarcompliance.com | H40: verified | I40: /in/david-lombardy-6472a5 | J40: New York New York | L40: 1 | M40: 54a7c107746869705aa89750
A41: Boutique compliance | B41: Calvin Robinson | C41: Managing Partner | D41: Quadrant Regulatory Group | E41: 3 | F41: quadrantregulatory.com | G41: crobinson@quadrantregulatory.com | H41: verified | I41: /in/calvinarobinson | J41: New York New York | K41: +1 646-930-1900 | L41: 1 | M41: 60fced195946ac0001a6fcd2
A42: Boutique compliance | B42: Glenn Marone | C42: Managing Partner | D42: Quadrant Regulatory Group | E42: 3 | F42: quadrantregulatory.com | G42: gmarone@quadrantregulatory.com | H42: verified | I42: /in/glennmarone | J42: Florida | K42: +1 646-930-1900 | L42: 1 | M42: 5dd1d040df729b000132215c
A43: Boutique compliance | B43: Nicholas Pallante | C43: Managing Director | D43: Quadrant Regulatory Group | E43: 3 | F43: quadrantregulatory.com | G43: npallante@quadrantregulatory.com | H43: verified | I43: /in/nicholas-pallante-b938047 | J43: New York New York | K43: +1 646-930-1900 | L43: 2 | M43: 54a1f6037468693825adf100
A44: Boutique compliance | B44: Gerard Clark | C44: Chief Executive Officer | D44: Regulatory Compliance LLC | E44: 1 | H44: unavailable | I44: /in/gerard-clark | J44: Massachusetts | L44: 1 | M44: 69f86d778476900001117acf
A45: Boutique compliance | B45: Ivan Barretto | C45: Founder and Managing Director | D45: RIA Compliance Concepts | E45: 1 | F45: riacc.io | G45: ivan@riacc.io | H45: verified | I45: /in/ivanbarretto30 | J45: Texas | K45: +1 833-742-2246 | L45: 1 | M45: 66f49ba68fa53f000177c729
A46: Boutique compliance | B46: Richard Rondano | C46: Managing Partner & Founder | D46: Risk & Compliance Consulting, LLC | E46: 1 | H46: unavailable | I46: /in/richardrondano | J46: New York New York | L46: 1 | M46: 54a78ec07468696de776e93f
A47: Boutique compliance | B47: Allison Gill | C47: Managing Director | D47: RQC Group | E47: 1 | F47: rqcgroup.com | G47: agill@rqcgroup.com | H47: verified | I47: /in/allison-gill-9860734 | J47: New York New York | K47: +44 20 7958 9127 | L47: 2 | M47: 55ce3188f3e5bb3733001ab1
A48: Boutique compliance | B48: Janaya Moscony | C48: President | D48: SEC Compliance Consultants, Inc. (SEC3) | E48: 1 | F48: sec3compliance.com | G48: janaya@sec3compliance.com | H48: verified | I48: /in/janayasec3 | J48: Miami Florida | K48: +1 212-706-4029 | L48: 2 | M48: 66f9a039d1c6fd00016868a1
A49: Boutique compliance | B49: Brian Kesselman | C49: Founder/CRO | D49: Skematic | E49: 2 | F49: skematic.com | G49: brian@skematic.com | H49: verified | I49: /in/brian-kesselman | J49: Miami Beach Florida | K49: +1 512-827-8254 | L49: 2 | M49: 66fe7e055898520001da76d6
A50: Boutique compliance | B50: Jon Lo | C50: Co-Founder & Managing Director | D50: StrategyBRIX | E50: 1 | F50: strategybrix.com | G50: jon@strategybrix.com | H50: verified | I50: /in/jon-lo-cams | J50: New York New York | L50: 2 | M50: 66f3e0438b93af0001c3aa17
A51: Boutique compliance | B51: Gerald Roop | C51: Principal | D51: Treliant (Acquired by Huron - 2025) | E51: 1 | F51: treliant.com | H51: unavailable | I51: /in/gerald-roop-285639b | J51: Fort Lauderdale Florida | K51: +1 202-249-7950 | L51: 2 | M51: 60c87b3f8862cf000156d890
A52: Boutique compliance | B52: Dorothy Dewitt | C52: Founder, CEO | D52: Tölt Strategies | E52: 1 | F52: toltstrategies.com | G52: dorothy.dewitt@toltstrategies.com | H52: verified | I52: /in/dorothydewitt | J52: New York New York | K52: +1 212-287-5810 | L52: 2 | M52: 66f14b49ed5ec3000144d0f7
A53: Boutique compliance | B53: Michael Evans | C53: Founder | D53: VEGA Compliance Consulting & Expert Witness | E53: 1 | F53: vegacompliance.com | G53: mike.evans@vegacompliance.com | H53: verified | I53: /in/mgevans | J53: New York New York | K53: +1 929-459-3680 | L53: 2 | M53: 5b2fab41a6da982cc18aa923
A54: Boutique compliance | B54: Joe Paul | C54: Principal and Assurance Practice Leader | D54: Venning | E54: 3 | F54: venningadvisors.com | G54: jpaul@venningadvisors.com | H54: verified | I54: /in/josephhpaul | J54: West Palm Beach Florida | K54: +1 410-329-6002 | L54: 2 | M54: 5ae28ebca6da984d18ffb36d
A55: Boutique compliance | B55: Mariela Reyes | C55: Principal | D55: Venning | E55: 3 | F55: venningadvisors.com | G55: mreyes@venningadvisors.com | H55: verified | I55: /in/mariela-reyes-1b286a17 | J55: Miami Beach Florida | K55: +1 410-329-6002 | L55: 2 | M55: 54ebfe9f746869431172be39
A56: Boutique compliance | B56: Amy Yuter | C56: Managing Principal | D56: Yuter Compliance Consulting | E56: 1 | F56: yutercompliance.com | G56: ayuter@yutercompliance.com | H56: verified | I56: /in/amy-yuter-b2284544 | J56: Philadelphia Pennsylvania | K56: +1 215-550-1508 | L56: 1 | M56: 54a4026074686938ac654325
A57: Compliance (national) | B57: Allison Jaffe | C57: Principal and Director of Compliance Programs | D57: 3iCO | E57: 1 | F57: 3ico.com | G57: ajaffe@3icollc.com | H57: verified | I57: /in/allison-jaffe-3ico | J57: New York New York | K57: +1 917-913-5619 | L57: 3 | M57: 54a7572d74686968294b7e2b
A58: Compliance (national) | B58: Andrew Fischer | C58: Director (Supervising Principal) | D58: ACA Foreside | E58: 5 | F58: foreside.com | G58: afischer@foreside.com | H58: verified | I58: /in/andrew-fischer-a3b59094 | J58: Portland Maine | K58: +1 207-553-7110 | L58: 4 | M58: 5ad631b9a6da98678272f4c6
A59: Compliance (national) | B59: Ashley Zeiher | C59: Principal Consultant | D59: ACA Foreside | E59: 5 | F59: foreside.com | H59: unavailable | I59: /in/ashleyzeiher | J59: Milwaukee Wisconsin | K59: +1 207-553-7110 | L59: 4 | M59: 57daa00da6da984a3449365a
A60: Compliance (national) | B60: Heather Hjelm | C60: Director (Supervisory Principal) | D60: ACA Foreside | E60: 5 | F60: foreside.com | H60: unavailable | I60: /in/heather-hjelm-b7b3b21a | J60: Garden City New York | K60: +1 207-553-7110 | L60: 4 | M60: 54a3d5617468693b8c4e7b16
A61: Compliance (national) | B61: Mary Ellen Dunn | C61: Senior Principal Consultant | D61: ACA Foreside | E61: 5 | F61: foreside.com | G61: maryellen.dunn@acaglobal.com | H61: verified | I61: /in/mary-ellen-dunn-79a69455 | J61: New York New York | K61: +1 207-553-7110 | L61: 4 | M61: 54a60aeb7468693b8c51febd
A62: Compliance (national) | B62: Richard Berthy | C62: Chief Executive Officer | D62: ACA Foreside | E62: 5 | G62: rberthy@foreside.com | H62: verified | I62: /in/richard-berthy-66812914 | J62: Portland Maine | K62: +1 207-553-7110 | L62: 3 | M62: 69befb6af4c27b0001a984c9
A63: Compliance (national) | B63: Tiffany Ramirez | C63: Founder and Managing Partner | D63: Adviser Solutions Group LLC | E63: 1 | F63: advisersolutionsgroup.com | H63: unavailable | I63: /in/tiffanylramirez | J63: Dallas Texas | K63: +1 214-909-2235 | L63: 3 | M63: 54ec1a54746869444c972150
A64: Compliance (national) | B64: Frances Meany | C64: Principal AML Consultant | D64: Aspect Advisors | E64: 6 | F64: aspectadv.com | G64: frances@aspectadv.com | H64: verified | I64: /in/frances-meany-cams-6a449997 | J64: Denver Colorado | K64: +1 415-423-3445 | L64: 3 | M64: 5e7908fc22a6910001843de4
A65: Compliance (national) | B65: Meredith Geldhauser | C65: Principal Consultant | D65: Aspect Advisors | E65: 6 | F65: aspectadv.com | G65: meredith@aspectadv.com | H65: verified | I65: /in/meredith-geldhauser | J65: Atlanta Georgia | K65: +1 415-423-3445 | L65: 3 | M65: 601bf24d67b2da0001e04b9b
A66: Compliance (national) | B66: Patrick Labbe | C66: Principal Compliance Consultant | D66: Aspect Advisors | E66: 6 | F66: aspectadv.com | G66: patrick@aspectadv.com | H66: verified | I66: /in/patrick-labbe-bb017067 | J66: Boston Massachusetts | K66: +1 415-423-3445 | L66: 3 | M66: 54a79295746869730a56ed41
A67: Compliance (national) | B67: Sami Oudeh | C67: Principal Compliance Consultant | D67: Aspect Advisors | E67: 6 | F67: aspectadv.com | H67: unavailable | I67: /in/samioudeh | J67: Lexington Kentucky | K67: +1 415-423-3445 | L67: 3 | M67: 60f21d3e152e7e0001ae1e2b
A68: Compliance (national) | B68: Carrie Rinehart-Bekker | C68: Founder, CEO, and Managing Member | D68: Bekker Compliance Consulting Partners, LLC | E68: 1 | F68: bccp-llc.com | G68: cbekker@bccp-llc.com | H68: verified | I68: /in/bekkercompliance | J68: Tampa Florida | K68: +1 818-836-1291 | L68: 3 | M68: 66f8e7ec8dcef000016881d8
A69: Compliance (national) | B69: Dan Denton | C69: Owner | D69: Business Compliance Partners | E69: 2 | F69: bizcompliancepartners.com | G69: dan@bizcompliancepartners.com | H69: verified | I69: /in/dan-denton-742a021b | J69: Baltimore Maryland | K69: +1 888-538-6088 | L69: 3 | M69: 612b99204c92050001d08b87
A70: Compliance (national) | B70: Paul Cox | C70: CEO | D70: Business Compliance Partners | E70: 2 | F70: bizcompliancepartners.com | G70: paul@bizcompliancepartners.com | H70: verified | I70: /in/paulcoxbcp | J70: San Diego California | K70: +1 888-538-6088 | L70: 3 | M70: 5b3d6221a6da98a0c267bc85
A71: Compliance (national) | B71: Robert Williams | C71: President | D71: Cohasset Associates, Inc. | E71: 2 | F71: cohasset.com | G71: robert.williams@cohasset.com | H71: verified | I71: /in/robert-f-williams-6227311b | J71: Chicago Illinois | K71: +1 952-445-7225 | L71: 4 | M71: 54a2c4d57468693a7e6eb43b
A72: Compliance (national) | B72: Teresa Drabenstadt | C72: Principal Consultant | D72: Cohasset Associates, Inc. | E72: 2 | F72: cohasset.com | G72: teresa.drabenstadt@cohasset.com | H72: verified | I72: /in/teresadrabenstadt | J72: Madison Wisconsin | K72: +1 952-445-7225 | L72: 4 | M72: 54a1271469702dc8418d0000
A73: Compliance (national) | B73: Craig Neal | C73: Founder | D73: Compliance Admins LLC | E73: 1 | F73: complianceadmins.com | G73: craig.neal@complianceadmins.com | H73: verified | I73: /in/craigneal | J73: Northbrook Illinois | K73: +1 847-877-0365 | L73: 3 | M73: 66fcde8248b83f0001081d27
A74: Compliance (national) | B74: Alvaro Pereyra | C74: Broker Dealer Chief Executive Officer | D74: Compliance Exchange Group (CXG) | E74: 2 | F74: cxgllc.com | G74: apereyra@cxgllc.com | H74: verified | I74: /in/alvaro-pereyra-7503a18 | J74: New York New York | K74: +1 631-595-5305 | L74: 3 | M74: 66f42f2032ac2a00019fbb70
A75: Compliance (national) | B75: Christopher Driscoll | C75: Executive, Founder | D75: Compliance Exchange Group (CXG) | E75: 2 | F75: cxgllc.com | G75: cdriscoll@cxgllc.com | H75: verified | I75: /in/christopher-driscoll-cxg | J75: Smithtown New York | K75: +1 631-595-5305 | L75: 3 | M75: 66ebe1a82d0d7800017cf778
A76: Compliance (national) | B76: David Amster | C76: Managing Principal | D76: Compliance Risk Concepts (CRC​) | E76: 4 | F76: compliance-risk.com | G76: damster@compliance-risk.com | H76: verified | I76: /in/davidamster | J76: New York New York | K76: +1 646-346-2468 | L76: 3 | M76: 557091f87369644c318d3100
A77: Compliance (national) | B77: Jaclyn Bowdren | C77: Managing Principal and Chief Operating Officer | D77: Compliance Risk Concepts (CRC​) | E77: 4 | F77: compliance-risk.com | G77: jbowdren@compliance-risk.com | H77: verified | I77: /in/jaclyn-bowdren-41608444 | J77: New York New York | K77: +1 646-346-2468 | L77: 3 | M77: 66fbfdc44996b80001363908
A78: Compliance (national) | B78: Mitch Avnet | C78: Managing Partner | D78: Compliance Risk Concepts (CRC​) | E78: 4 | F78: compliance-risk.com | G78: mavnet@compliance-risk.com | H78: verified | I78: /in/mitchavnet | J78: New York New York | K78: +1 646-346-2468 | L78: 3 | M78: 6093fa15871d9c000161159f
A79: Compliance (national) | B79: Scott Brown | C79: Associate Director/Financial & Operations Principal | D79: Compliance Risk Concepts (CRC​) | E79: 4 | F79: compliance-risk.com | G79: sbrown@compliance-risk.com | H79: verified | I79: /in/series27 | J79: New York New York | K79: +1 646-346-2468 | L79: 3 | M79: 5eeea0fbd171f50001b57067
... A94: Compliance (national) | B94: Scott Homuth | C94: SVP / Regulatory & Compliance Practice Lead | D94: FITS Consulting | E94: 1 | F94: fitsconsulting.com | G94: shomuth@fitsconsulting.com | H94: verified | I94: /in/smhomuth | J94: Charlotte North Carolina | K94: +1 973-586-8877 | L94: 4 | M94: 57d41e17a6da98536ed77b1d
A95: Compliance (national) | B95: Chip Arvantides | C95: Executive Vice President | D95: FrontLine Compliance | E95: 1 | F95: frontlinecompliance.com | H95: unavailable | I95: /in/chip-arvantides-3a61098 | J95: Rockville Maryland | K95: +1 888-518-8070 | L95: 4 | M95: 66f885db1cc13a0001e8fd7e
A96: Compliance (national) | B96: Amy Jones | C96: Founder, Principal | D96: Guardian Performance Solutions LLC | E96: 2 | F96: guardianperformancesolutions.com | G96: amy@compliantperformance.com | H96: verified | I96: /in/amyjonescipm | J96: Seattle Washington | K96: +1 206-456-2464 | L96: 3 | M96: 54a21bf374686930c2af550d
A97: Compliance (national) | B97: Arin Stancil | C97: Managing Director, Principal | D97: Guardian Performance Solutions LLC | E97: 2 | F97: guardianperformancesolutions.com | G97: arin@compliantperformance.com | H97: verified | I97: /in/arin-stancil-cfa-cipm-37b16911 | J97: Seattle Washington | K97: +1 206-456-2464 | L97: 4 | M97: 54a62ec67468693676f56dc8
A98: Compliance (national) | B98: Stacie Craddock | C98: Founder & Senior Principal Consultant | D98: Integrated Compliance Advisors, Ltd. | E98: 1 | F98: integrated-compliance.com | G98: stacie@integrated-compliance.com | H98: verified | I98: /in/stacie-craddock-17124298 | J98: Boulder Colorado | K98: +1 720-759-3535 | L98: 3 | M98: 5efe0f1f1d1a3b00beb0b9bc
A99: Compliance (national) | B99: David Millar | C99: Owner: RIA Registration and Consulting Company | D99: Integrity Compliance Consulting, Inc. | E99: 1 | F99: riamadeeasy.com | G99: dmillar@integrity2c.com | H99: verified | I99: /in/millardavidr | J99: Grand Rapids Michigan | K99: +1 616-855-5560 | L99: 4 | M99: 54a79ff07468696de7f86146
A100: Compliance (national) | B100: Beverly Fetcko | C100: Vice President | D100: NCS Regulatory Compliance (now part of Foreside) | E100: 1 | F100: foreside.com | H100: unavailable | I100: /in/beverlyfetcko | J100: Fort Wayne Indiana | K100: +1 484-320-6239 | L100: 3 | M100: 65fa7cdb1cb67f00064d0a22
A101: Compliance (national) | B101: Anthony Visone | C101: Principal | D101: Optima Partners | E101: 5 | F101: optima-partners.com | G101: anthony.visone@optima-partners.com | H101: verified | I101: /in/anthony-visone-337449b0 | J101: New York New York | K101: +1 646-205-6380 | L101: 3 | M101: 54eb326574686931e2b96c0b
A102: Compliance (national) | B102: Beata Valouktzis | C102: Principal | D102: Optima Partners | E102: 5 | F102: optima-partners.com | G102: betty.valouktzis@optima-partners.com | H102: verified | I102: /in/beata-betty-valouktzis-6b982516 | J102: New York New York | K102: +1 646-205-6380 | L102: 3 | M102: 54a4ff5c7468692cf02b8374
A103: Compliance (national) | B103: Sara McLean | C103: VP of Business Development - Cybersecurity | D103: Optima Partners | E103: 5 | F103: optima-partners.com | G103: sara.mclean@optima-partners.com | H103: verified | I103: /in/sara-mclean-38b336bb | J103: Denver Colorado | K103: +1 646-205-6380 | L103: 3 | M103: 5c49a694a3ae61116dc08950
A104: Compliance (national) | B104: Gregory Florio | C104: Co-Managing Member, Founder | D104: Orical LLC | E104: 1 | F104: orical.org | G104: gflorio@florioleahy.com | H104: verified | I104: /in/gregory-florio-6854433b | J104: New York New York | L104: 3 | M104: 5ff97d97cbf6550001326750
A105: Compliance (national) | B105: Buddy Doyle | C105: Founding Principal - Managing Director | D105: Oyster Consulting, LLC | E105: 8 | F105: oysterllc.com | G105: buddy.doyle@oysterllc.com | H105: verified | I105: /in/buddydoyle | J105: Richmond Virginia | K105: +1 804-965-5400 | L105: 4 | M105: 54c287fe7468697af7a858a5
A106: Compliance (national) | B106: David Williams | C106: Managing Principal | D106: Oyster Consulting, LLC | E106: 8 | F106: oysterllc.com | G106: david.williams@oysterllc.com | H106: verified | I106: /in/david-williams-112a051b | J106: Richmond Virginia | K106: +1 804-965-5400 | L106: 4 | M106: 66f8346af3aaa200011eae3b
A107: Compliance (national) | B107: Patrick Dennis | C107: Founder | D107: Oyster Consulting, LLC | E107: 8 | F107: oysterllc.com | G107: patrick.dennis@oysterllc.com | H107: verified | I107: /in/patrickmdennis | J107: Glen Allen Virginia | K107: +1 804-965-5400 | L107: 3 | M107: 60f5e8e87ef4d50001bb0f18
A108: Compliance (national) | B108: Rob Hall | C108: Founding Principal & Managing Director | D108: Oyster Consulting, LLC | E108: 8 | F108: oysterllc.com | G108: robert.hall@oysterllc.com | H108: verified | I108: /in/robhalloyster | J108: Glen Allen Virginia | K108: +1 804-965-5400 | L108: 4 | M108: 5b3f8969a6da98f1ff33cf99
A109: Compliance (national) | B109: Deirdre Patten | C109: President/Owner | D109: Patten Training & Review | E109: 2 | F109: pattentraining.com | G109: dpatten@pattentraining.com | H109: verified | I109: /in/deirdre-patten-65ba755 | J109: Spring Texas | K109: +1 281-419-6030 | L109: 3 | M109: 66f750481c88dc0001d5b26d
A110: Compliance (national) | B110: Ivana Shumberg | C110: Principal | D110: Patten Training & Review | E110: 2 | F110: pattentraining.com | G110: ishumberg@pattentraining.com | H110: verified | I110: /in/ivana-shumberg-2b9868307 | J110: Leander Texas | K110: +1 281-419-6030 | L110: 3 | M110: 66a088c7c139af0001fac142
A111: Compliance (national) | B111: Deacon Durden | C111: President/Owner | D111: QCS Financial Services | E111: 2 | F111: qcsfinancialservices.com | G111: deacon@qcsfinancialservices.com | H111: extrapolated | I111: /in/deacon-john-durden-5b6a8517 | J111: Livermore California | K111: +1 925-447-7666 | L111: 3 | M111: 66fd0d50348f810001b60bdf
A112: Compliance (national) | B112: John Durden | C112: President | D112: QCS Financial Services | E112: 2 | F112: qcsfinancialservices.com | H112: unavailable | I112: /in/john-durden-35080678 | J112: Livermore California | K112: +1 925-447-7666 | L112: 3 | M112: 66f6affea3fccf0001e6e50f
A113: Compliance (national) | B113: Kent Keister | C113: Founder & Principal Consultant | D113: Reliant Compliance | E113: 1 | F113: reliantcompliance.com | G113: kent@reliantcompliance.com | H113: verified | I113: /in/kent-keister | J113: Columbus Ohio | K113: +1 614-259-8077 | L113: 3 | M113: 65966ec9d503db00015cf5b8
A114: Compliance (national) | B114: Jarrod James | C114: Senior Vice President | D114: RIA Compliance Consultants, Inc. | E114: 1 | F114: ria-compliance-consultants.com | G114: jjames@ria-compliance-consultants.com | H114: verified | I114: /in/jarrodjames | J114: Omaha Nebraska | K114: +1 877-345-4034 | L114: 3 | M114: 66f9af78d1c6fd00016d2295
...

Sheet Send List
A1: Tier | B1: Name | C1: Title | D1: Firm | E1: Work email | F1: Email status | G1: LinkedIn profile | H1: Channel | I1: Alternates at firm | J1: Owner | K1: Status | L1: Date contacted | M1: Notes
A2: Boutique compliance | B2: Vick Ekizian | C2: Founder and CEO | D2: 5 Pillars Compliance Consulting, LLC | E2: vick@5pillarscompliance.com | F2: verified | G2: /in/vickekizian | H2: Email | I2: 0
A3: Boutique compliance | B3: Lisa Roitman | C3: Managing Partner | D3: Abide Consulting Group | E3: lisa@abidegrp.com | F3: verified | G3: /in/lisaroitman | H3: Email | I3: 2
A4: Boutique compliance | B4: Robert Masi | C4: Managing Partner | D4: Accordo | E4: robert.masi@accordo.solutions | F4: verified | G4: /in/robert-masi-1a123b8 | H4: Email | I4: 0
A5: Boutique compliance | B5: Stephen Lurie | C5: Principal Owner | D5: Adviser Compliance Consulting | F5: unavailable | G5: /in/stephen-lurie-8b0b371 | H5: LinkedIn only | I5: 1
A6: Boutique compliance | B6: Joseph Stowell | C6: Managing Partner, President | D6: Ally Compliance Partners LLC | E6: joe@allycompliancepartners.com | F6: verified | G6: /in/josephstowell | H6: Email | I6: 0
A7: Boutique compliance | B7: Chris Hardy | C7: Co-Founder | D7: altPILOT Group | E7: chris@altpilotgroup.com | F7: verified | G7: /in/chrishardy2 | H7: Email | I7: 1
A8: Boutique compliance | B8: Jon Hurd | C8: Founder, Chief Executive Officer and Certified Anti-Money Laundering Specialist | D8: Asgard Regulatory Group, LLC | E8: jhurd@asgardcompliance.com | F8: verified | G8: /in/jonhurdarg | H8: Email | I8: 2
A9: Boutique compliance | B9: Justin Schleifer | C9: President, Co-Founder | D9: Aspect Advisors | E9: justin@aspectadv.com | F9: verified | G9: /in/justin-schleifer-28852036 | H9: Email | I9: 5
A10: Boutique compliance | B10: Chris Nowak | C10: Founder & CEO | D10: Augmenta Prime | E10: chris.nowak@augmentaprimegroup.com | F10: verified | G10: /in/chris-nowak-cams-cafp-cbp | H10: Email | I10: 0
A11: Boutique compliance | B11: Stefanie Little | C11: Founder & Managing Partner | D11: Chenery Compliance Group | E11: slittle@chenerycompliance.com | F11: verified | G11: /in/stefanie-j-little-b155075 | H11: Email | I11: 3
A12: Boutique compliance | B12: Claire McCleskey | C12: Co-Founder | D12: Clarity Compliance Consulting | E12: com@clarity-consultancy.com | F12: verified | G12: /in/claire-o-neill-mccleskey | H12: Email | I12: 0
A13: Boutique compliance | B13: David Martin | C13: Founder/CEO | D13: Compliers Consulting Services, LLC | E13: david@compliers.com | F13: verified | G13: /in/davidjaindlmartin | H13: Email | I13: 1
A14: Boutique compliance | B14: Michelle Jacko | C14: CEO | D14: Core Compliance & Legal Services, Inc. | E14: michelle.jacko@corecls.com | F14: verified | G14: /in/michellejacko | H14: Email | I14: 0
A15: Boutique compliance | B15: Gary Fox | C15: Managing Director and Partner | D15: DFP Partners | E15: gfox@dfppartners.com | F15: verified | G15: /in/garyfox8 | H15: Email | I15: 1
A16: Boutique compliance | B16: Francesco Matteini | C16: CEO and Founder | D16: InnReg | E16: francesco@innreg.com | F16: verified | G16: /in/fmatteini | H16: Email | I16: 1
A17: Boutique compliance | B17: Stephen Murphy | C17: Managing Director | D17: Integrated Compliance Consulting | E17: smurphy@icc-comply.com | F17: verified | G17: /in/stephen-murphy-cfa-9903874 | H17: Email | I17: 1
... A27: Boutique compliance | B27: Calvin Robinson | C27: Managing Partner | D27: Quadrant Regulatory Group | E27: crobinson@quadrantregulatory.com | F27: verified | G27: /in/calvinarobinson | H27: Email | I27: 2
A28: Boutique compliance | B28: Gerard Clark | C28: Chief Executive Officer | D28: Regulatory Compliance LLC | F28: unavailable | G28: /in/gerard-clark | H28: LinkedIn only | I28: 0
A29: Boutique compliance | B29: Ivan Barretto | C29: Founder and Managing Director | D29: RIA Compliance Concepts | E29: ivan@riacc.io | F29: verified | G29: /in/ivanbarretto30 | H29: Email | I29: 0
A30: Boutique compliance | B30: Richard Rondano | C30: Managing Partner & Founder | D30: Risk & Compliance Consulting, LLC | F30: unavailable | G30: /in/richardrondano | H30: LinkedIn only | I30: 0
A31: Boutique compliance | B31: Allison Gill | C31: Managing Director | D31: RQC Group | E31: agill@rqcgroup.com | F31: verified | G31: /in/allison-gill-9860734 | H31: Email | I31: 0
A32: Boutique compliance | B32: Janaya Moscony | C32: President | D32: SEC Compliance Consultants, Inc. (SEC3) | E32: janaya@sec3compliance.com | F32: verified | G32: /in/janayasec3 | H32: Email | I32: 0
A33: Boutique compliance | B33: Brian Kesselman | C33: Founder/CRO | D33: Skematic | E33: brian@skematic.com | F33: verified | G33: /in/brian-kesselman | H33: Email | I33: 1
A34: Boutique compliance | B34: Jon Lo | C34: Co-Founder & Managing Director | D34: StrategyBRIX | E34: jon@strategybrix.com | F34: verified | G34: /in/jon-lo-cams | H34: Email | I34: 0
A35: Boutique compliance | B35: Gerald Roop | C35: Principal | D35: Treliant (Acquired by Huron - 2025) | F35: unavailable | G35: /in/gerald-roop-285639b | H35: LinkedIn only | I35: 0
A36: Boutique compliance | B36: Dorothy Dewitt | C36: Founder, CEO | D36: Tölt Strategies | E36: dorothy.dewitt@toltstrategies.com | F36: verified | G36: /in/dorothydewitt | H36: Email | I36: 0
A37: Boutique compliance | B37: Michael Evans | C37: Founder | D37: VEGA Compliance Consulting & Expert Witness | E37: mike.evans@vegacompliance.com | F37: verified | G37: /in/mgevans | H37: Email | I37: 0
A38: Boutique compliance | B38: Joe Paul | C38: Principal and Assurance Practice Leader | D38: Venning | E38: jpaul@venningadvisors.com | F38: verified | G38: /in/josephhpaul | H38: Email | I38: 2
A39: Boutique compliance | B39: Amy Yuter | C39: Managing Principal | D39: Yuter Compliance Consulting | E39: ayuter@yutercompliance.com | F39: verified | G39: /in/amy-yuter-b2284544 | H39: Email | I39: 0
A40: Compliance (national) | B40: Allison Jaffe | C40: Principal and Director of Compliance Programs | D40: 3iCO | E40: ajaffe@3icollc.com | F40: verified | G40: /in/allison-jaffe-3ico | H40: Email | I40: 0
A41: Compliance (national) | B41: Richard Berthy | C41: Chief Executive Officer | D41: ACA Foreside | E41: rberthy@foreside.com | F41: verified | G41: /in/richard-berthy-66812914 | H41: Email | I41: 4
A42: Compliance (national) | B42: Tiffany Ramirez | C42: Founder and Managing Partner | D42: Adviser Solutions Group LLC | F42: unavailable | G42: /in/tiffanylramirez | H42: LinkedIn only | I42: 0
A43: Compliance (national) | B43: Carrie Rinehart-Bekker | C43: Founder, CEO, and Managing Member | D43: Bekker Compliance Consulting Partners, LLC | E43: cbekker@bccp-llc.com | F43: verified | G43: /in/bekkercompliance | H43: Email | I43: 0
A44: Compliance (national) | B44: Dan Denton | C44: Owner | D44: Business Compliance Partners | E44: dan@bizcompliancepartners.com | F44: verified | G44: /in/dan-denton-742a021b | H44: Email | I44: 1
A45: Compliance (national) | B45: Robert Williams | C45: President | D45: Cohasset Associates, Inc. | E45: robert.williams@cohasset.com | F45: verified | G45: /in/robert-f-williams-6227311b | H45: Email | I45: 1
A46: Compliance (national) | B46: Craig Neal | C46: Founder | D46: Compliance Admins LLC | E46: craig.neal@complianceadmins.com | F46: verified | G46: /in/craigneal | H46: Email | I46: 0
A47: Compliance (national) | B47: Alvaro Pereyra | C47: Broker Dealer Chief Executive Officer | D47: Compliance Exchange Group (CXG) | E47: apereyra@cxgllc.com | F47: verified | G47: /in/alvaro-pereyra-7503a18 | H47: Email | I47: 1
A48: Compliance (national) | B48: Mitch Avnet | C48: Managing Partner | D48: Compliance Risk Concepts (CRC​) | E48: mavnet@compliance-risk.com | F48: verified | G48: /in/mitchavnet | H48: Email | I48: 3
A49: Compliance (national) | B49: Peter Guarino | C49: President / Chief Compliance Officer | D49: Compliance4 | E49: pguarino@compliance4.com | F49: verified | G49: /in/peterguarino | H49: Email | I49: 0
A50: Compliance (national) | B50: Cathy Cucharale | C50: President | D50: Cucharale Consulting Group | E50: ccucharale@cucharalegroup.com | F50: verified | G50: /in/cathy-a-cucharale | H50: Email | I50: 0
A51: Compliance (national) | B51: Jeff Chapman | C51: Founding Partner, Executive Vice President, | D51: Dinsmore Compliance Services | E51: jeff.chapman@dinsmorecomplianceservices.com | F51: verified | G51: /in/jeffchapman2 | H51: Email | I51: 4
A52: Compliance (national) | B52: Lance Mackenzie | C52: President | D52: eAdvisor Compliance | E52: lance@eadvisorcompliance.com | F52: verified | G52: /in/lancemackenzie | H52: Email | I52: 0
A53: Compliance (national) | B53: Todd Spillane | C53: President | D53: Essential Edge Compliance Outsourcing Services, LLC | E53: todd@eefirms.com | F53: verified | G53: /in/todd-spillane-336a373 | H53: Email | I53: 0
A54: Compliance (national) | B54: Neil Reithinger | C54: President | D54: Eventus Advisory Group, LLC | E54: nreithinger@eventusag.com | F54: verified | G54: /in/neil-reithinger-2849833 | H54: Email | I54: 0
... A56: Compliance (national) | B56: Scott Homuth | C56: SVP / Regulatory & Compliance Practice Lead | D56: FITS Consulting | E56: shomuth@fitsconsulting.com | F56: verified | G56: /in/smhomuth | H56: Email | I56: 0
A57: Compliance (national) | B57: Chip Arvantides | C57: Executive Vice President | D57: FrontLine Compliance | F57: unavailable | G57: /in/chip-arvantides-3a61098 | H57: LinkedIn only | I57: 0
A58: Compliance (national) | B58: Amy Jones | C58: Founder, Principal | D58: Guardian Performance Solutions LLC | E58: amy@compliantperformance.com | F58: verified | G58: /in/amyjonescipm | H58: Email | I58: 1
A59: Compliance (national) | B59: Stacie Craddock | C59: Founder & Senior Principal Consultant | D59: Integrated Compliance Advisors, Ltd. | E59: stacie@integrated-compliance.com | F59: verified | G59: /in/stacie-craddock-17124298 | H59: Email | I59: 0
A60: Compliance (national) | B60: David Millar | C60: Owner: RIA Registration and Consulting Company | D60: Integrity Compliance Consulting, Inc. | E60: dmillar@integrity2c.com | F60: verified | G60: /in/millardavidr | H60: Email | I60: 0
A61: Compliance (national) | B61: Beverly Fetcko | C61: Vice President | D61: NCS Regulatory Compliance (now part of Foreside) | F61: unavailable | G61: /in/beverlyfetcko | H61: LinkedIn only | I61: 0
A62: Compliance (national) | B62: Gregory Florio | C62: Co-Managing Member, Founder | D62: Orical LLC | E62: gflorio@florioleahy.com | F62: verified | G62: /in/gregory-florio-6854433b | H62: Email | I62: 0
A63: Compliance (national) | B63: Patrick Dennis | C63: Founder | D63: Oyster Consulting, LLC | E63: patrick.dennis@oysterllc.com | F63: verified | G63: /in/patrickmdennis | H63: Email | I63: 7
A64: Compliance (national) | B64: Deirdre Patten | C64: President/Owner | D64: Patten Training & Review | E64: dpatten@pattentraining.com | F64: verified | G64: /in/deirdre-patten-65ba755 | H64: Email | I64: 1
A65: Compliance (national) | B65: Deacon Durden | C65: President/Owner | D65: QCS Financial Services | E65: deacon@qcsfinancialservices.com | F65: extrapolated | G65: /in/deacon-john-durden-5b6a8517 | H65: LinkedIn (email unverified) | I65: 1
A66: Compliance (national) | B66: Kent Keister | C66: Founder & Principal Consultant | D66: Reliant Compliance | E66: kent@reliantcompliance.com | F66: verified | G66: /in/kent-keister | H66: Email | I66: 0
A67: Compliance (national) | B67: Jarrod James | C67: Senior Vice President | D67: RIA Compliance Consultants, Inc. | E67: jjames@ria-compliance-consultants.com | F67: verified | G67: /in/jarrodjames | H67: Email | I67: 0
A68: Compliance (national) | B68: Blake Bjordahl | C68: RIA Technology Evangelist | Compliance Specialist | Co-Founder | FinTech & CompTech | D68: RIA Compliance Technology | E68: blake@riacomp.com | F68: verified | G68: /in/blakebjordahl | H68: Email | I68: 0
A69: Compliance (national) | B69: Elizabeth Cope | C69: CEO & Lead Compliance Consultant | D69: SEC Compliance Solutions LLC | E69: liz@seccsllc.com | F69: verified | G69: /in/elizabeth-cope-cpa-cipm-cscp-b521bb8 | H69: Email | I69: 1
A70: Compliance (national) | B70: Stephen Simon | C70: President | D70: Securities Compliance Advisors | E70: ssimon@secadvisors.com | F70: extrapolated | G70: /in/stephen-simon-92301812 | H70: LinkedIn (email unverified) | I70: 0
A71: Compliance (national) | B71: Kyle Weeks | C71: Owner | D71: Securities Compliance Management | E71: kyle.weeks@mastercompliance.com | F71: verified | G71: /in/kyleweeks63 | H71: Email | I71: 0
A72: Compliance (national) | B72: Fizza Khan | C72: Chief Executive Officer | D72: Silver Regulatory Associates LLC | E72: fkhan@silverreg.com | F72: verified | G72: /in/fizzakhan1 | H72: Email | I72: 0
A73: Compliance (national) | B73: Maureen James | C73: Owner | D73: Summit Compliance Group, LLC | E73: mjames@summitcompliancegroup.com | F73: verified | G73: /in/maureenjames1 | H73: Email | I73: 0
A74: Enterprise compliance | B74: Trey Loughran | C74: Chief Executive Officer | D74: ACA Group | E74: trey.loughran@acaglobal.com | F74: verified | G74: /in/treyloughran | H74: Email | I74: 1
A75: Enterprise compliance | B75: Jay Haas | C75: Managing Director | D75: Cipperman Compliance Services, LLC (now part of Foreside) | F75: unavailable | G75: /in/jay-haas-a7560a17 | H75: LinkedIn only | I75: 0
A76: Compliance + legal | B76: Brian Hamburger | C76: Founder & Chief Executive Officer | D76: MarketCounsel Consulting | E76: summit@marketcounsel.com | F76: verified | G76: /in/hamburger | H76: Email | I76: 2
A77: Cyber / E&O broker | B77: Kenneth Golsan | C77: Co-Founder & Managing Director | D77: Golsan Scruggs | E77: kgolsan@golsanscruggs.com | F77: verified | G77: /in/kenneth-golsan-46555520 | H77: Email | I77: 1
A78: Cyber / E&O broker | B78: Andrea Dyer | C78: CEO and President | D78: HCP National Insurance Services, Inc. | E78: crisl@hcpnational.com | F78: verified | G78: /in/andrea-%e2%80%9ccris%e2%80%9d-dyer-06b58233 | H78: Email | I78: 1
A79: Cyber / E&O broker | B79: Nathan Borghardt | C79: AVP-Business Development Executive | D79: Lockton Affinity | E79: nborghardt@locktonaffinity.com | F79: verified | G79: /in/nathan-borghardt-95224253 | H79: Email | I79: 2
A80: Cyber / E&O broker | B80: Karen Coyle | C80: Vice President of Operations | D80: The Coyle Group | E80: karen@thecoylegroup.com | F80: verified | G80: /in/karen-coyle-b7679376 | H80: Email | I80: 1
A81: RIA platform | B81: Harris Baltch | C81: Managing Director, Co-Head of Investment Banking | D81: Dynasty Financial Partners | E81: hbaltch@dynastyfp.com | F81: verified | G81: /in/harrisbaltch | H81: Email | I81: 2
A82: RIA platform | B82: Eric Nothstein | C82: Managing Director, Head of Business Development | D82: Sanctuary Wealth | E82: enothstein@sanctuarywealth.com | F82: verified | G82: /in/eric-nothstein-6098bb14 | H82: Email | I82: 4
A83: Fund administrator | B83: Casper Calisin | C83: Managing Director | D83: HC Global Fund Services, LLC | E83: ccalisin@hcglobalfs.com | F83: verified | G83: /in/casper-calisin-61a2b19 | H83: Email | I83: 1
A84: Fund administrator | B84: Nav Gupta | C84: CEO | D84: NAV Fund Services | E84: nav@navconsulting.net | F84: verified | G84: /in/nav-gupta-6b385b7 | H84: Email | I84: 1
A85: Fund administrator | B85: Robert Ansell | C85: Director, Business Development | D85: Opus Fund Services | E85: ransell@opusfundservices.com | F85: verified | G85: /in/robert-ansell-015aab255 | H85: Email | I85: 2
A86: RIA M&A advisor | B86: Brandon Kawal | C86: Partner | D86: Advisor Growth Strategies LLC | E86: bkawal@advisorgrowthllc.com | F86: verified | G86: /in/brandonkawal | H86: Email | I86: 0
A87: RIA M&A advisor | B87: Gordon Ross | C87: President | D87: DeVoe & Company | E87: gordon.ross@devoe-co.com | F87: verified | G87: /in/gordonross-gla | H87: Email | I87: 4
A88: Securities counsel | B88: Patricia Klusmeyer | C88: Partner | D88: Parker MacIntyre | E88: pklusmeyer@parkmac.com | F88: verified | G88: /in/patricia-klusmeyer-4b6915b | H88: Email | I88: 1
A89: Securities counsel | B89: John Macdonald | C89: Partner/Shareholder | D89: Stark & Stark | F89: unavailable | G89: /in/john-macdonald-683a0b15 | H89: LinkedIn only | I89: 0
A90: Adjacent / weaker fit | B90: Hanh Nguyen | C90: Founder | D90: Complect | E90: hanh@complect.com | F90: verified | G90: /in/hanh-t-nguyen | H90: Email | I90: 0
A91: Adjacent / weaker fit | B91: Wilfredo Rodriguez | C91: CEO and Founder | D91: DSF Advisors LLC | E91: wrodriguez@dsfadv.com | F91: verified | G91: /in/wilfredocpa | H91: Email | I91: 0
A92: Adjacent / weaker fit | B92: Matthew Lourie | C92: Founder and CEO | D92: Fresh Notion Group | E92: mlourie@freshnotiongroup.com | F92: verified | G92: /in/matthew-lourie-19b12a15 | H92: Email | I92: 0
A93: Adjacent / weaker fit | B93: Matthew Judge | C93: CEO and Founder | D93: Genesis Filings, LLC | E93: mjudge@genesisfilings.com | F93: verified | G93: /in/matthew-judge74 | H93: Email | I93: 0
A94: Adjacent / weaker fit | B94: George Quinn | C94: CEO & Founder | D94: TBH Consulting LLC | E94: george.quinn@tbhconsulting.com | F94: verified | G94: /in/george-quinn-72158389 | H94: Email | I94: 0
